roboweb_extension/__init__.py
roboweb_extension/_version.py
roboweb_extension/labextension/package.json
roboweb_extension/labextension/static/568.8aa90f90bd8fe74e17a2.js
roboweb_extension/labextension/static/remoteEntry.52495129d51f16d70f5d.js
roboweb_extension/labextension/static/style.js
roboweb_extension/labextension/static/third-party-licenses.json
roboweb_extension-0.1.42.data/data/share/jupyter/labextensions/roboweb-extension/install.json
roboweb_extension-0.1.42.data/data/share/jupyter/labextensions/roboweb-extension/package.json
roboweb_extension-0.1.42.data/data/share/jupyter/labextensions/roboweb-extension/static/568.8aa90f90bd8fe74e17a2.js
roboweb_extension-0.1.42.data/data/share/jupyter/labextensions/roboweb-extension/static/remoteEntry.52495129d51f16d70f5d.js
roboweb_extension-0.1.42.data/data/share/jupyter/labextensions/roboweb-extension/static/style.js
roboweb_extension-0.1.42.data/data/share/jupyter/labextensions/roboweb-extension/static/third-party-licenses.json
roboweb_extension-0.1.42.dist-info/METADATA
roboweb_extension-0.1.42.dist-info/WHEEL
roboweb_extension-0.1.42.dist-info/licenses/LICENSE
roboweb_extension-0.1.42.dist-info/RECORD
