Metadata-Version: 2.1
Name: roboweb-extension
Version: 0.1.42
Summary: Roboweb JupyterLab extension
Project-URL: Homepage, https://roboweb.app/
Author-email: Francisco Uribe <francisco.uribe@gmail.com>
License-File: LICENSE
Keywords: Jupyter,JupyterLab,JupyterLab3
Classifier: Framework :: Jupyter
Classifier: Framework :: Jupyter :: JupyterLab
Classifier: Framework :: Jupyter :: JupyterLab :: 3
Classifier: Framework :: Jupyter :: JupyterLab :: Extensions
Classifier: Framework :: Jupyter :: JupyterLab :: Extensions :: Prebuilt
Classifier: License :: OSI Approved :: BSD License
Classifier: Programming Language :: Python
Classifier: Programming Language :: Python :: 3
Classifier: Programming Language :: Python :: 3.7
Classifier: Programming Language :: Python :: 3.8
Classifier: Programming Language :: Python :: 3.9
Classifier: Programming Language :: Python :: 3.10
Requires-Python: >=3.7
